{
  "generatedAt": "2026-05-13T16:51:38.153Z",
  "sync": {
    "destination": "strava",
    "lastImportedAt": "2026-05-13T16:48:52.727Z",
    "lastSyncedAt": "2026-05-13T16:51:37.893Z",
    "routePrivacy": {
      "hideRoutes": false,
      "trimEndMeters": 0,
      "trimStartMeters": 0
    },
    "source": "keep"
  },
  "totals": {
    "distanceMeters": 676040,
    "elevationGainMeters": 0,
    "movingTimeSeconds": 134517,
    "rides": 44
  },
  "version": 1,
  "years": [
    {
      "distanceMeters": 42140,
      "elevationGainMeters": 0,
      "movingTimeSeconds": 9263,
      "rides": 7,
      "year": 2026
    },
    {
      "distanceMeters": 181680,
      "elevationGainMeters": 0,
      "movingTimeSeconds": 38809,
      "rides": 24,
      "year": 2025
    },
    {
      "distanceMeters": 452220,
      "elevationGainMeters": 0,
      "movingTimeSeconds": 86445,
      "rides": 13,
      "year": 2024
    }
  ]
}
